[
  {
    "outputFile": "Shared/MainLayout.razor.css",
    "inputFile": "Shared/MainLayout.razor.scss"
  },
  {
    "outputFile": "Shared/AppErrorBoundary.razor.css",
    "inputFile": "Shared/AppErrorBoundary.razor.scss"
  },
  {
    "outputFile": "Shared/MessageBox.razor.css",
    "inputFile": "Shared/MessageBox.razor.scss"
  },
  {
    "outputFile": "Shared/Header.razor.css",
    "inputFile": "Shared/Header.razor.scss"
  },
  {
    "outputFile": "Shared/Footer.razor.css",
    "inputFile": "Shared/Footer.razor.scss"
  },
  {
    "outputFile": "Shared/NavMenu.razor.css",
    "inputFile": "Shared/NavMenu.razor.scss"
  },
  {
    "outputFile": "Shared/SignOutConfirmModal.razor.css",
    "inputFile": "Shared/SignOutConfirmModal.razor.scss"
  },
  {
    "outputFile": "Shared/PageNotFound.razor.css",
    "inputFile": "Shared/PageNotFound.razor.scss"
  },
  {
    "outputFile": "Pages/HomePage.razor.css",
    "inputFile": "Pages/HomePage.razor.scss"
  },
  {
    "outputFile": "Components/BarInfoMetric.razor.css",
    "inputFile": "Components/BarInfoMetric.razor.scss"
  },
  {
    "outputFile": "Pages/WalletPage.razor.css",
    "inputFile": "Pages/WalletPage.razor.scss"
  },
  {
    "outputFile": "Shared/MiniLoading.razor.css",
    "inputFile": "Shared/MiniLoading.razor.scss"
  },
  {
    "outputFile": "Shared/TrxInfoCard.razor.css",
    "inputFile": "Shared/TrxInfoCard.razor.scss"
  }
]